Workbook

Sheet DimCustomers
A1: CustomerID | B1: Name | C1: Gender | D1: Country | E1: Email | F1: PhoneNumber
A2: CUST0000 | B2: Norma Fisher | C2: Female | D2: Gabon | E2: bsellers@yahoo.com | F2: 001-273-949-1441x969
A3: CUST0001 | B3: Jorge Sullivan | C3: Female | D3: Namibia | E3: robert39@yahoo.com | F3: 001-196-911-4038
A4: CUST0002 | B4: Elizabeth Woods | C4: Male | D4: Mayotte | E4: oturner@garcia.com | F4: +1-819-651-9927
A5: CUST0003 | B5: Susan Wagner | C5: Female | D5: Eritrea | E5: gregory93@ramsey.com | F5: 001-269-676-7086x963
A6: CUST0004 | B6: Peter Montgomery | C6: Female | D6: Norfolk Island | E6: steven85@yahoo.com | F6: 701.156.5273x9167
A7: CUST0005 | B7: Theodore Mcgrath | C7: Female | D7: South Georgia and the South Sandwich Islands | E7: pjones@hotmail.com | F7: 865.996.0080x34759
A8: CUST0006 | B8: Stephanie Collins | C8: Female | D8: Tajikistan | E8: mwilliams@robbins-long.com | F8: 992-127-4904x75322
A9: CUST0007 | B9: Stephanie Sutton | C9: Female | D9: Namibia | E9: ashley19@hotmail.com | F9: 790-387-2786x79673
A10: CUST0008 | B10: Brian Hamilton | C10: Female | D10: Saint Lucia | E10: leonardmarie@jimenez.com | F10: 621-551-0174
A11: CUST0009 | B11: Susan Levy | C11: Male | D11: Oman | E11: murphyanthony@hotmail.com | F11: +1-349-980-7748x4704
A12: CUST0010 | B12: Sean Green | C12: Male | D12: New Caledonia | E12: markmooney@wright.org | F12: 121.999.9029
... A3001: CUST2999 | B3001: Rickey Cameron | C3001: Female | D3001: Tonga | E3001: brian77@yahoo.com | F3001: 840-959-8864

Sheet DimVisaApplications
A1: VisaID | B1: VisaType | C1: Status | D1: CountryApplied | E1: SubmissionDate | F1: ApprovedDate | G1: Fees | H1: proccessinf time
A2: VISA0000 | B2: Business | C2: Rejected | D2: Canada | E2: 45861 | F2: 45873 | G2: 1138 | H2: =Table4[[#This Row],[ApprovedDate]]-Table4[[#This Row],[SubmissionDate]] -> 12
A3: VISA0001 | B3: Business | C3: Rejected | D3: France | E3: 45829 | F3: 45868 | G3: 1766 | H3: =Table4[[#This Row],[ApprovedDate]]-Table4[[#This Row],[SubmissionDate]] -> 39
A4: VISA0002 | B4: Student | C4: Rejected | D4: UK | E4: 45596 | F4: 45880 | G4: 1656 | H4: =Table4[[#This Row],[ApprovedDate]]-Table4[[#This Row],[SubmissionDate]] -> 284
A5: VISA0003 | B5: Student | C5: Approved | D5: France | E5: 45822 | F5: 45877 | G5: 1872 | H5: =Table4[[#This Row],[ApprovedDate]]-Table4[[#This Row],[SubmissionDate]] -> 55
A6: VISA0004 | B6: Student | C6: Pending | D6: UAE | E6: 45853 | F6: 45870 | G6: 1515 | H6: =Table4[[#This Row],[ApprovedDate]]-Table4[[#This Row],[SubmissionDate]] -> 17
A7: VISA0005 | B7: Tourist | C7: Approved | D7: Canada | E7: 45614 | G7: 1683 | H7: =Table4[[#This Row],[ApprovedDate]]-Table4[[#This Row],[SubmissionDate]] -> -45614
A8: VISA0006 | B8: Tourist | C8: Pending | D8: UAE | E8: 45776 | F8: 45889 | G8: 858 | H8: =Table4[[#This Row],[ApprovedDate]]-Table4[[#This Row],[SubmissionDate]] -> 113
A9: VISA0007 | B9: Business | C9: Rejected | D9: Canada | E9: 45539 | F9: 45872 | G9: 1763 | H9: =Table4[[#This Row],[ApprovedDate]]-Table4[[#This Row],[SubmissionDate]] -> 333
A10: VISA0008 | B10: Student | C10: Pending | D10: France | E10: 45825 | F10: 45884 | G10: 1701 | H10: =Table4[[#This Row],[ApprovedDate]]-Table4[[#This Row],[SubmissionDate]] -> 59
A11: VISA0009 | B11: Business | C11: Pending | D11: Germany | E11: 45793 | F11: 45878 | G11: 1046 | H11: =Table4[[#This Row],[ApprovedDate]]-Table4[[#This Row],[SubmissionDate]] -> 85
A12: VISA0010 | B12: Business | C12: Rejected | D12: UK | E12: 45509 | G12: 882 | H12: =Table4[[#This Row],[ApprovedDate]]-Table4[[#This Row],[SubmissionDate]] -> -45509
A13: VISA0011 | B13: Student | C13: Pending | D13: France | E13: 45789 | F13: 45870 | G13: 904 | H13: =Table4[[#This Row],[ApprovedDate]]-Table4[[#This Row],[SubmissionDate]] -> 81
A14: VISA0012 | B14: Student | C14: Rejected | D14: UAE | E14: 45568 | F14: 45890 | G14: 532 | H14: =Table4[[#This Row],[ApprovedDate]]-Table4[[#This Row],[SubmissionDate]] -> 322
A15: VISA0013 | B15: Student | C15: Rejected | D15: Germany | E15: 45781 | G15: 1932 | H15: =Table4[[#This Row],[ApprovedDate]]-Table4[[#This Row],[SubmissionDate]] -> -45781
A16: VISA0014 | B16: Tourist | C16: Pending | D16: Canada | E16: 45680 | G16: 1179 | H16: =Table4[[#This Row],[ApprovedDate]]-Table4[[#This Row],[SubmissionDate]] -> -45680
A17: VISA0015 | B17: Business | C17: Approved | D17: UAE | E17: 45577 | F17: 45886 | G17: 1926 | H17: =Table4[[#This Row],[ApprovedDate]]-Table4[[#This Row],[SubmissionDate]] -> 309
A18: VISA0016 | B18: Tourist | C18: Pending | D18: USA | E18: 45637 | G18: 1654 | H18: =Table4[[#This Row],[ApprovedDate]]-Table4[[#This Row],[SubmissionDate]] -> -45637
A19: VISA0017 | B19: Student | C19: Approved | D19: France | E19: 45750 | F19: 45880 | G19: 1864 | H19: =Table4[[#This Row],[ApprovedDate]]-Table4[[#This Row],[SubmissionDate]] -> 130
A20: VISA0018 | B20: Tourist | C20: Approved | D20: Canada | E20: 45730 | F20: 45884 | G20: 908 | H20: =Table4[[#This Row],[ApprovedDate]]-Table4[[#This Row],[SubmissionDate]] -> 154
A21: VISA0019 | B21: Tourist | C21: Approved | D21: Canada | E21: 45509 | F21: 45862 | G21: 1446 | H21: =Table4[[#This Row],[ApprovedDate]]-Table4[[#This Row],[SubmissionDate]] -> 353
A22: VISA0020 | B22: Tourist | C22: Approved | D22: USA | E22: 45508 | F22: 45890 | G22: 1226 | H22: =Table4[[#This Row],[ApprovedDate]]-Table4[[#This Row],[SubmissionDate]] -> 382
A23: VISA0021 | B23: Business | C23: Rejected | D23: Germany | E23: 45839 | F23: 45880 | G23: 634 | H23: =Table4[[#This Row],[ApprovedDate]]-Table4[[#This Row],[SubmissionDate]] -> 41
A24: VISA0022 | B24: Tourist | C24: Approved | D24: Canada | E24: 45653 | F24: 45888 | G24: 1472 | H24: =Table4[[#This Row],[ApprovedDate]]-Table4[[#This Row],[SubmissionDate]] -> 235
A25: VISA0023 | B25: Tourist | C25: Pending | D25: USA | E25: 45796 | F25: 45868 | G25: 1435 | H25: =Table4[[#This Row],[ApprovedDate]]-Table4[[#This Row],[SubmissionDate]] -> 72
A26: VISA0024 | B26: Tourist | C26: Pending | D26: UAE | E26: 45555 | G26: 1244 | H26: =Table4[[#This Row],[ApprovedDate]]-Table4[[#This Row],[SubmissionDate]] -> -45555
A27: VISA0025 | B27: Business | C27: Approved | D27: France | E27: 45673 | G27: 570 | H27: =Table4[[#This Row],[ApprovedDate]]-Table4[[#This Row],[SubmissionDate]] -> -45673
A28: VISA0026 | B28: Business | C28: Pending | D28: Germany | E28: 45559 | F28: 45863 | G28: 1579 | H28: =Table4[[#This Row],[ApprovedDate]]-Table4[[#This Row],[SubmissionDate]] -> 304
A29: VISA0027 | B29: Tourist | C29: Pending | D29: Canada | E29: 45708 | F29: 45886 | G29: 897 | H29: =Table4[[#This Row],[ApprovedDate]]-Table4[[#This Row],[SubmissionDate]] -> 178
A30: VISA0028 | B30: Student | C30: Rejected | D30: France | E30: 45858 | F30: 45889 | G30: 644 | H30: =Table4[[#This Row],[ApprovedDate]]-Table4[[#This Row],[SubmissionDate]] -> 31
A31: VISA0029 | B31: Student | C31: Pending | D31: UAE | E31: 45704 | F31: 45875 | G31: 934 | H31: =Table4[[#This Row],[ApprovedDate]]-Table4[[#This Row],[SubmissionDate]] -> 171
A32: VISA0030 | B32: Tourist | C32: Rejected | D32: France | E32: 45652 | G32: 1476 | H32: =Table4[[#This Row],[ApprovedDate]]-Table4[[#This Row],[SubmissionDate]] -> -45652
A33: VISA0031 | B33: Tourist | C33: Pending | D33: Canada | E33: 45750 | G33: 823 | H33: =Table4[[#This Row],[ApprovedDate]]-Table4[[#This Row],[SubmissionDate]] -> -45750
A34: VISA0032 | B34: Student | C34: Rejected | D34: France | E34: 45599 | G34: 734 | H34: =Table4[[#This Row],[ApprovedDate]]-Table4[[#This Row],[SubmissionDate]] -> -45599
A35: VISA0033 | B35: Business | C35: Pending | D35: Germany | E35: 45847 | F35: 45889 | G35: 1953 | H35: =Table4[[#This Row],[ApprovedDate]]-Table4[[#This Row],[SubmissionDate]] -> 42
A36: VISA0034 | B36: Student | C36: Approved | D36: France | E36: 45733 | F36: 45882 | G36: 1417 | H36: =Table4[[#This Row],[ApprovedDate]]-Table4[[#This Row],[SubmissionDate]] -> 149
A37: VISA0035 | B37: Tourist | C37: Pending | D37: UAE | E37: 45844 | F37: 45866 | G37: 1543 | H37: =Table4[[#This Row],[ApprovedDate]]-Table4[[#This Row],[SubmissionDate]] -> 22
A38: VISA0036 | B38: Student | C38: Pending | D38: UAE | E38: 45498 | G38: 551 | H38: =Table4[[#This Row],[ApprovedDate]]-Table4[[#This Row],[SubmissionDate]] -> -45498
A39: VISA0037 | B39: Business | C39: Pending | D39: UK | E39: 45705 | G39: 1902 | H39: =Table4[[#This Row],[ApprovedDate]]-Table4[[#This Row],[SubmissionDate]] -> -45705
A40: VISA0038 | B40: Tourist | C40: Pending | D40: USA | E40: 45582 | F40: 45869 | G40: 525 | H40: =Table4[[#This Row],[ApprovedDate]]-Table4[[#This Row],[SubmissionDate]] -> 287
A41: VISA0039 | B41: Business | C41: Pending | D41: Germany | E41: 45532 | F41: 45873 | G41: 729 | H41: =Table4[[#This Row],[ApprovedDate]]-Table4[[#This Row],[SubmissionDate]] -> 341
A42: VISA0040 | B42: Business | C42: Pending | D42: UK | E42: 45532 | G42: 922 | H42: =Table4[[#This Row],[ApprovedDate]]-Table4[[#This Row],[SubmissionDate]] -> -45532
A43: VISA0041 | B43: Tourist | C43: Rejected | D43: UK | E43: 45743 | F43: 45883 | G43: 689 | H43: =Table4[[#This Row],[ApprovedDate]]-Table4[[#This Row],[SubmissionDate]] -> 140
A44: VISA0042 | B44: Business | C44: Approved | D44: Germany | E44: 45742 | F44: 45888 | G44: 1311 | H44: =Table4[[#This Row],[ApprovedDate]]-Table4[[#This Row],[SubmissionDate]] -> 146
A45: VISA0043 | B45: Business | C45: Approved | D45: Germany | E45: 45568 | F45: 45866 | G45: 561 | H45: =Table4[[#This Row],[ApprovedDate]]-Table4[[#This Row],[SubmissionDate]] -> 298
A46: VISA0044 | B46: Tourist | C46: Pending | D46: France | E46: 45700 | F46: 45868 | G46: 788 | H46: =Table4[[#This Row],[ApprovedDate]]-Table4[[#This Row],[SubmissionDate]] -> 168
A47: VISA0045 | B47: Business | C47: Rejected | D47: France | E47: 45823 | G47: 1260 | H47: =Table4[[#This Row],[ApprovedDate]]-Table4[[#This Row],[SubmissionDate]] -> -45823
A48: VISA0046 | B48: Tourist | C48: Approved | D48: Germany | E48: 45781 | F48: 45889 | G48: 1893 | H48: =Table4[[#This Row],[ApprovedDate]]-Table4[[#This Row],[SubmissionDate]] -> 108
A49: VISA0047 | B49: Tourist | C49: Rejected | D49: Germany | E49: 45720 | F49: 45885 | G49: 1099 | H49: =Table4[[#This Row],[ApprovedDate]]-Table4[[#This Row],[SubmissionDate]] -> 165
A50: VISA0048 | B50: Student | C50: Pending | D50: UK | E50: 45515 | F50: 45862 | G50: 1002 | H50: =Table4[[#This Row],[ApprovedDate]]-Table4[[#This Row],[SubmissionDate]] -> 347
A51: VISA0049 | B51: Student | C51: Rejected | D51: USA | E51: 45756 | F51: 45871 | G51: 576 | H51: =Table4[[#This Row],[ApprovedDate]]-Table4[[#This Row],[SubmissionDate]] -> 115
A52: VISA0050 | B52: Tourist | C52: Pending | D52: UK | E52: 45741 | F52: 45868 | G52: 744 | H52: =Table4[[#This Row],[ApprovedDate]]-Table4[[#This Row],[SubmissionDate]] -> 127
A53: VISA0051 | B53: Business | C53: Pending | D53: UK | E53: 45589 | F53: 45878 | G53: 1161 | H53: =Table4[[#This Row],[ApprovedDate]]-Table4[[#This Row],[SubmissionDate]] -> 289
A54: VISA0052 | B54: Student | C54: Pending | D54: UAE | E54: 45710 | F54: 45889 | G54: 969 | H54: =Table4[[#This Row],[ApprovedDate]]-Table4[[#This Row],[SubmissionDate]] -> 179
A55: VISA0053 | B55: Business | C55: Approved | D55: France | E55: 45752 | G55: 923 | H55: =Table4[[#This Row],[ApprovedDate]]-Table4[[#This Row],[SubmissionDate]] -> -45752
A56: VISA0054 | B56: Student | C56: Approved | D56: UK | E56: 45771 | F56: 45875 | G56: 1032 | H56: =Table4[[#This Row],[ApprovedDate]]-Table4[[#This Row],[SubmissionDate]] -> 104
A57: VISA0055 | B57: Business | C57: Approved | D57: UAE | E57: 45569 | G57: 1690 | H57: =Table4[[#This Row],[ApprovedDate]]-Table4[[#This Row],[SubmissionDate]] -> -45569
A58: VISA0056 | B58: Tourist | C58: Rejected | D58: UAE | E58: 45575 | F58: 45880 | G58: 1300 | H58: =Table4[[#This Row],[ApprovedDate]]-Table4[[#This Row],[SubmissionDate]] -> 305
A59: VISA0057 | B59: Tourist | C59: Rejected | D59: Canada | E59: 45856 | F59: 45870 | G59: 1775 | H59: =Table4[[#This Row],[ApprovedDate]]-Table4[[#This Row],[SubmissionDate]] -> 14
A60: VISA0058 | B60: Student | C60: Pending | D60: France | E60: 45544 | F60: 45882 | G60: 1921 | H60: =Table4[[#This Row],[ApprovedDate]]-Table4[[#This Row],[SubmissionDate]] -> 338
A61: VISA0059 | B61: Business | C61: Rejected | D61: France | E61: 45817 | F61: 45878 | G61: 1218 | H61: =Table4[[#This Row],[ApprovedDate]]-Table4[[#This Row],[SubmissionDate]] -> 61
A62: VISA0060 | B62: Business | C62: Pending | D62: USA | E62: 45698 | G62: 1938 | H62: =Table4[[#This Row],[ApprovedDate]]-Table4[[#This Row],[SubmissionDate]] -> -45698
A63: VISA0061 | B63: Business | C63: Approved | D63: UAE | E63: 45658 | F63: 45878 | G63: 1594 | H63: =Table4[[#This Row],[ApprovedDate]]-Table4[[#This Row],[SubmissionDate]] -> 220
A64: VISA0062 | B64: Student | C64: Rejected | D64: Canada | E64: 45563 | F64: 45870 | G64: 957 | H64: =Table4[[#This Row],[ApprovedDate]]-Table4[[#This Row],[SubmissionDate]] -> 307
A65: VISA0063 | B65: Tourist | C65: Rejected | D65: UAE | E65: 45572 | F65: 45867 | G65: 958 | H65: =Table4[[#This Row],[ApprovedDate]]-Table4[[#This Row],[SubmissionDate]] -> 295
A66: VISA0064 | B66: Tourist | C66: Approved | D66: France | E66: 45655 | G66: 743 | H66: =Table4[[#This Row],[ApprovedDate]]-Table4[[#This Row],[SubmissionDate]] -> -45655
A67: VISA0065 | B67: Business | C67: Pending | D67: USA | E67: 45647 | G67: 1719 | H67: =Table4[[#This Row],[ApprovedDate]]-Table4[[#This Row],[SubmissionDate]] -> -45647
A68: VISA0066 | B68: Business | C68: Pending | D68: USA | E68: 45704 | F68: 45881 | G68: 1707 | H68: =Table4[[#This Row],[ApprovedDate]]-Table4[[#This Row],[SubmissionDate]] -> 177
A69: VISA0067 | B69: Business | C69: Pending | D69: Canada | E69: 45610 | F69: 45887 | G69: 1749 | H69: =Table4[[#This Row],[ApprovedDate]]-Table4[[#This Row],[SubmissionDate]] -> 277
A70: VISA0068 | B70: Business | C70: Pending | D70: Canada | E70: 45529 | F70: 45871 | G70: 1641 | H70: =Table4[[#This Row],[ApprovedDate]]-Table4[[#This Row],[SubmissionDate]] -> 342
A71: VISA0069 | B71: Student | C71: Pending | D71: UAE | E71: 45699 | G71: 817 | H71: =Table4[[#This Row],[ApprovedDate]]-Table4[[#This Row],[SubmissionDate]] -> -45699
A72: VISA0070 | B72: Business | C72: Rejected | D72: USA | E72: 45607 | F72: 45881 | G72: 1102 | H72: =Table4[[#This Row],[ApprovedDate]]-Table4[[#This Row],[SubmissionDate]] -> 274
A73: VISA0071 | B73: Business | C73: Pending | D73: Canada | E73: 45740 | F73: 45870 | G73: 1775 | H73: =Table4[[#This Row],[ApprovedDate]]-Table4[[#This Row],[SubmissionDate]] -> 130
A74: VISA0072 | B74: Tourist | C74: Pending | D74: UK | E74: 45700 | F74: 45873 | G74: 1726 | H74: =Table4[[#This Row],[ApprovedDate]]-Table4[[#This Row],[SubmissionDate]] -> 173
A75: VISA0073 | B75: Business | C75: Rejected | D75: UAE | E75: 45611 | F75: 45884 | G75: 1424 | H75: =Table4[[#This Row],[ApprovedDate]]-Table4[[#This Row],[SubmissionDate]] -> 273
A76: VISA0074 | B76: Tourist | C76: Rejected | D76: USA | E76: 45607 | F76: 45872 | G76: 1235 | H76: =Table4[[#This Row],[ApprovedDate]]-Table4[[#This Row],[SubmissionDate]] -> 265
A77: VISA0075 | B77: Business | C77: Approved | D77: UAE | E77: 45679 | F77: 45884 | G77: 1259 | H77: =Table4[[#This Row],[ApprovedDate]]-Table4[[#This Row],[SubmissionDate]] -> 205
A78: VISA0076 | B78: Student | C78: Pending | D78: UK | E78: 45632 | F78: 45875 | G78: 1822 | H78: =Table4[[#This Row],[ApprovedDate]]-Table4[[#This Row],[SubmissionDate]] -> 243
A79: VISA0077 | B79: Tourist | C79: Approved | D79: UK | E79: 45629 | G79: 1424 | H79: =Table4[[#This Row],[ApprovedDate]]-Table4[[#This Row],[SubmissionDate]] -> -45629
A80: VISA0078 | B80: Business | C80: Rejected | D80: France | E80: 45815 | F80: 45884 | G80: 975 | H80: =Table4[[#This Row],[ApprovedDate]]-Table4[[#This Row],[SubmissionDate]] -> 69
A81: VISA0079 | B81: Tourist | C81: Rejected | D81: UAE | E81: 45829 | F81: 45884 | G81: 1244 | H81: =Table4[[#This Row],[ApprovedDate]]-Table4[[#This Row],[SubmissionDate]] -> 55
A82: VISA0080 | B82: Tourist | C82: Rejected | D82: Canada | E82: 45526 | F82: 45875 | G82: 1899 | H82: =Table4[[#This Row],[ApprovedDate]]-Table4[[#This Row],[SubmissionDate]] -> 349
A83: VISA0081 | B83: Business | C83: Approved | D83: Canada | E83: 45521 | F83: 45875 | G83: 1948 | H83: =Table4[[#This Row],[ApprovedDate]]-Table4[[#This Row],[SubmissionDate]] -> 354
A84: VISA0082 | B84: Business | C84: Pending | D84: Canada | E84: 45765 | F84: 45867 | G84: 1191 | H84: =Table4[[#This Row],[ApprovedDate]]-Table4[[#This Row],[SubmissionDate]] -> 102
A85: VISA0083 | B85: Business | C85: Rejected | D85: Germany | E85: 45594 | F85: 45863 | G85: 1268 | H85: =Table4[[#This Row],[ApprovedDate]]-Table4[[#This Row],[SubmissionDate]] -> 269
A86: VISA0084 | B86: Business | C86: Approved | D86: UK | E86: 45782 | F86: 45876 | G86: 1732 | H86: =Table4[[#This Row],[ApprovedDate]]-Table4[[#This Row],[SubmissionDate]] -> 94
A87: VISA0085 | B87: Business | C87: Approved | D87: Canada | E87: 45821 | G87: 529 | H87: =Table4[[#This Row],[ApprovedDate]]-Table4[[#This Row],[SubmissionDate]] -> -45821
A88: VISA0086 | B88: Business | C88: Rejected | D88: Canada | E88: 45527 | G88: 1987 | H88: =Table4[[#This Row],[ApprovedDate]]-Table4[[#This Row],[SubmissionDate]] -> -45527
A89: VISA0087 | B89: Tourist | C89: Approved | D89: UK | E89: 45756 | F89: 45880 | G89: 809 | H89: =Table4[[#This Row],[ApprovedDate]]-Table4[[#This Row],[SubmissionDate]] -> 124
A90: VISA0088 | B90: Tourist | C90: Rejected | D90: Germany | E90: 45689 | F90: 45891 | G90: 1964 | H90: =Table4[[#This Row],[ApprovedDate]]-Table4[[#This Row],[SubmissionDate]] -> 202
A91: VISA0089 | B91: Business | C91: Pending | D91: UAE | E91: 45824 | F91: 45864 | G91: 1272 | H91: =Table4[[#This Row],[ApprovedDate]]-Table4[[#This Row],[SubmissionDate]] -> 40
A92: VISA0090 | B92: Tourist | C92: Rejected | D92: UAE | E92: 45832 | F92: 45869 | G92: 1819 | H92: =Table4[[#This Row],[ApprovedDate]]-Table4[[#This Row],[SubmissionDate]] -> 37
A93: VISA0091 | B93: Student | C93: Pending | D93: France | E93: 45734 | F93: 45883 | G93: 1922 | H93: =Table4[[#This Row],[ApprovedDate]]-Table4[[#This Row],[SubmissionDate]] -> 149
A94: VISA0092 | B94: Business | C94: Pending | D94: Germany | E94: 45724 | F94: 45868 | G94: 1451 | H94: =Table4[[#This Row],[ApprovedDate]]-Table4[[#This Row],[SubmissionDate]] -> 144
A95: VISA0093 | B95: Tourist | C95: Approved | D95: Germany | E95: 45773 | G95: 1242 | H95: =Table4[[#This Row],[ApprovedDate]]-Table4[[#This Row],[SubmissionDate]] -> -45773
A96: VISA0094 | B96: Business | C96: Approved | D96: UK | E96: 45859 | G96: 1460 | H96: =Table4[[#This Row],[ApprovedDate]]-Table4[[#This Row],[SubmissionDate]] -> -45859
A97: VISA0095 | B97: Tourist | C97: Pending | D97: Canada | E97: 45575 | G97: 1081 | H97: =Table4[[#This Row],[ApprovedDate]]-Table4[[#This Row],[SubmissionDate]] -> -45575
A98: VISA0096 | B98: Tourist | C98: Approved | D98: Germany | E98: 45563 | F98: 45889 | G98: 684 | H98: =Table4[[#This Row],[ApprovedDate]]-Table4[[#This Row],[SubmissionDate]] -> 326
A99: VISA0097 | B99: Student | C99: Pending | D99: UK | E99: 45603 | F99: 45872 | G99: 1619 | H99: =Table4[[#This Row],[ApprovedDate]]-Table4[[#This Row],[SubmissionDate]] -> 269
A100: VISA0098 | B100: Student | C100: Approved | D100: UAE | E100: 45811 | G100: 716 | H100: =Table4[[#This Row],[ApprovedDate]]-Table4[[#This Row],[SubmissionDate]] -> -45811
...

Sheet DimHotels
A1: HotelID | B1: HotelName | C1: City | D1: Country | E1: NightlyRate
A2: HOTEL0000 | B2: Hilton | C2: Cairo | D2: Philippines | E2: 390
A3: HOTEL0001 | B3: Four Seasons | C3: New York | D3: Senegal | E3: 551
A4: HOTEL0002 | B4: Radisson | C4: Cairo | D4: Bolivia | E4: 699
A5: HOTEL0003 | B5: Marriott | C5: Dubai | D5: Lao People's Democratic Republic | E5: 299
A6: HOTEL0004 | B6: Marriott | C6: Cairo | D6: Jersey | E6: 599
A7: HOTEL0005 | B7: Four Seasons | C7: London | D7: Pakistan | E7: 314
A8: HOTEL0006 | B8: Radisson | C8: Cairo | D8: Samoa | E8: 143
A9: HOTEL0007 | B9: Radisson | C9: New York | D9: Cocos (Keeling) Islands | E9: 437
A10: HOTEL0008 | B10: Four Seasons | C10: Dubai | D10: Zambia | E10: 108
A11: HOTEL0009 | B11: Marriott | C11: London | D11: Maldives | E11: 797
A12: HOTEL0010 | B12: Radisson | C12: London | D12: Sri Lanka | E12: 295
A13: HOTEL0011 | B13: Four Seasons | C13: London | D13: Guyana | E13: 521
... A3001: HOTEL2999 | B3001: Radisson | C3001: Cairo | D3001: Belgium | E3001: 213
A3002: {=_xlfn.UNIQUE(Table3[[#Data],[#Totals],[HotelID]])} -> #NAME? | E3002: =SUBTOTAL(101,Table3[NightlyRate]) -> 449.896

Sheet DimTickets
A1: TicketID | B1: FromCity | C1: ToCity | D1: DepartureDate | E1: Airline | F1: Class | G1: TicketCost
A2: TICK0000 | B2: Paris | C2: Paris | D2: 45862 | E2: British Airways | F2: Business | G2: 4955
A3: TICK0001 | B3: Cairo | C3: New York | D3: 45913 | E3: Air France | F3: First | G3: 1898
A4: TICK0002 | B4: Cairo | C4: London | D4: 45915 | E4: British Airways | F4: Business | G4: 2264
A5: TICK0003 | B5: New York | C5: Cairo | D5: 45886 | E5: Emirates | F5: Economy | G5: 3326
A6: TICK0004 | B6: Dubai | C6: Paris | D6: 45907 | E6: British Airways | F6: Business | G6: 2514
A7: TICK0005 | B7: London | C7: Cairo | D7: 45904 | E7: Air France | F7: Business | G7: 2998
A8: TICK0006 | B8: Dubai | C8: New York | D8: 45871 | E8: Emirates | F8: Business | G8: 1512
A9: TICK0007 | B9: Paris | C9: London | D9: 45875 | E9: Air France | F9: Economy | G9: 1209
A10: TICK0008 | B10: Dubai | C10: Dubai | D10: 45863 | E10: Air France | F10: First | G10: 1318
A11: TICK0009 | B11: Cairo | C11: Cairo | D11: 45894 | E11: Lufthansa | F11: Business | G11: 3373
A12: TICK0010 | B12: London | C12: Dubai | D12: 45898 | E12: Air France | F12: First | G12: 1592
A13: TICK0011 | B13: New York | C13: Dubai | D13: 45890 | E13: Lufthansa | F13: Economy | G13: 4357
... A3001: TICK2999 | B3001: London | C3001: Paris | D3001: 45916 | E3001: Lufthansa | F3001: First | G3001: 4661

Sheet Pivot
A1: Which countries are the top destinations for visa applications? | F1: Which city had the highest number of hotel bookings? | I1: What's the gender breakdown of customers who booked the most services?
A2: What is the total revenue from visa application fees? | F2: Row Labels | G2: Count of City
A3: Row Labels | B3: Top destinations | C3: Total Revenue | F3: Cairo | G3: 659 | I3: Row Labels | J3: Sum of Visa Fees | K3: Sum of Night Rate | L3: Sum of Ticket cost | M3: Sum of Tot cost
A4: France | B4: 541 | C4: 678406 | F4: London | G4: 625 | I4: Female | J4: 1930904 | K4: 711142 | L4: 4764618 | M4: 7406664
A5: USA | B5: 523 | C5: 634727 | F5: Paris | G5: 602 | I5: Male | J5: 1781370 | K5: 647165 | L5: 4226881 | M5: 6655416
A6: Canada | B6: 493 | C6: 618044 | F6: New York | G6: 598 | I6: Grand Total | J6: 3712274 | K6: 1358307 | L6: 8991499 | M6: 14062080
A7: UAE | B7: 493 | C7: 590464 | F7: Dubai | G7: 516 | I7: What is the total amount spent per customer (visa + hotel + ticket)?
A8: Germany | B8: 492 | C8: 623660 | F8: Grand Total | G8: 3000 | I8: Row Labels | J8: Sum of Tot cost
A9: UK | B9: 458 | C9: 566973 | I9: CUST0000 | J9: 4941
A10: Grand Total | B10: 3000 | C10: 3712274 | F10: Which country has the most customers? | I10: CUST0002 | J10: 4761 | L10: Which cities are most visited after visa approval?
F11: Row Labels | G11: Count of National Country | I11: CUST0006 | J11: 6560 | L11: Count of City | M11: Column Labels
F12: Nicaragua | G12: 28 | I12: CUST0007 | J12: 3880 | L12: Row Labels | M12: Approved | N12: Pending | O12: Rejected | P12: Grand Total
A13: How many visa applications were submitted each month? | F13: Bhutan | G13: 27 | I13: CUST0008 | J13: 4494 | L13: Cairo | M13: 226 | N13: 195 | O13: 238 | P13: 659
A14: Row Labels | B14: Count of VisaID | F14: Hong Kong | G14: 26 | I14: CUST0009 | J14: 4610 | L14: London | M14: 219 | N14: 206 | O14: 200 | P14: 625
A15: Jan | B15: 272 | F15: Azerbaijan | G15: 25 | I15: CUST0011 | J15: 5230 | L15: Paris | M15: 184 | N15: 219 | O15: 199 | P15: 602
A16: Feb | B16: 225 | F16: New Caledonia | G16: 25 | I16: CUST0013 | J16: 3513 | L16: New York | M16: 187 | N16: 194 | O16: 217 | P16: 598
A17: Mar | B17: 216 | F17: Senegal | G17: 24 | I17: CUST0014 | J17: 12365 | L17: Dubai | M17: 168 | N17: 165 | O17: 183 | P17: 516
A18: Apr | B18: 257 | F18: South Africa | G18: 24 | I18: CUST0015 | J18: 22219 | L18: Grand Total | M18: 984 | N18: 979 | O18: 1037 | P18: 3000
A19: May | B19: 246 | F19: Sierra Leone | G19: 23 | I19: CUST0016 | J19: 5110
A20: Jun | B20: 294 | F20: Russian Federation | G20: 23 | I20: CUST0018 | J20: 10079 | L20: What is the correlation between visa approval and spending on hotels?
A21: Jul | B21: 265 | F21: Maldives | G21: 23 | I21: CUST0019 | J21: 11325 | L21: Sum of Night Rate | M21: Column Labels
A22: Aug | B22: 264 | F22: Bouvet Island (Bouvetoya) | G22: 22 | I22: CUST0021 | J22: 6904 | L22: Row Labels | M22: Approved | N22: Pending | O22: Rejected | P22: Grand Total
A23: Sep | B23: 254 | F23: Solomon Islands | G23: 21 | I23: CUST0022 | J23: 10213 | L23: Four Seasons | M23: 75886 | N23: 76755 | O23: 83926 | P23: 236567
A24: Oct | B24: 249 | F24: Ethiopia | G24: 21 | I24: CUST0023 | J24: 14710 | L24: Hilton | M24: 99886 | N24: 103438 | O24: 97423 | P24: 300747
A25: Nov | B25: 203 | F25: Andorra | G25: 21 | I25: CUST0024 | J25: 5189 | L25: Marriott | M25: 85383 | N25: 82265 | O25: 87556 | P25: 255204
A26: Dec | B26: 255 | F26: Suriname | G26: 21 | I26: CUST0025 | J26: 4199 | L26: Radisson | M26: 85046 | N26: 88153 | O26: 90503 | P26: 263702
A27: Grand Total | B27: 3000 | F27: Iran | G27: 21 | I27: CUST0026 | J27: 4104 | L27: Sheraton | M27: 100887 | N27: 90525 | O27: 110675 | P27: 302087
F28: Kyrgyz Republic | G28: 21 | I28: CUST0027 | J28: 2133 | L28: Grand Total | M28: 447088 | N28: 441136 | O28: 470083 | P28: 1358307
A29: Are there customers who booked only a visa but not hotel or flight? | E29: No | F29: Gabon | G29: 20 | I29: CUST0028 | J29: 18211
A30: Count of BookingID | B30: Count of CustomerID | C30: Count of VisaID | D30: Count of TicketID | E30: Count of HotelID | F30: Djibouti | G30: 20 | I30: CUST0030 | J30: 2105
A31: 3000 | B31: 3000 | C31: 3000 | D31: 3000 | E31: 3000 | F31: Guinea | G31: 20 | I31: CUST0031 | J31: 18250
F32: Cape Verde | G32: 20 | I32: CUST0032 | J32: 3026
A33: Do customers who get visa approvals also book flights and hotels with us? | E33: Yes | F33: Ireland | G33: 20 | I33: CUST0036 | J33: 17293
A34: Row Labels | B34: Count of Visa Status | C34: Count of HotelID | D34: Count of TicketID | F34: Saint Vincent and the Grenadines | G34: 19 | I34: CUST0037 | J34: 5915
A35: Approved | B35: 984 | C35: 984 | D35: 984 | F35: Jamaica | G35: 19 | I35: CUST0039 | J35: 2233
A36: Pending | B36: 979 | C36: 979 | D36: 979 | F36: Spain | G36: 19 | I36: CUST0040 | J36: 10209
A37: Rejected | B37: 1037 | C37: 1037 | D37: 1037 | F37: France | G37: 19 | I37: CUST0041 | J37: 3600
A38: Grand Total | B38: 3000 | C38: 3000 | D38: 3000 | F38: Montenegro | G38: 19 | I38: CUST0042 | J38: 5928
F39: Georgia | G39: 19 | I39: CUST0043 | J39: 6136
A40: What is the average total cost per complete booking (visa + hotel + flight)? | F40: Slovenia | G40: 19 | I40: CUST0044 | J40: 5374
A41: Row Labels | B41: Average of Tot cost2 | F41: Cote d'Ivoire | G41: 19 | I41: CUST0046 | J41: 2765
A42: BOOK0000 | B42: 6969 | F42: Argentina | G42: 19 | I42: CUST0048 | J42: 5998
A43: BOOK0001 | B43: 4709 | F43: Latvia | G43: 19 | I43: CUST0050 | J43: 10063
A44: BOOK0002 | B44: 4165 | F44: Qatar | G44: 18 | I44: CUST0052 | J44: 4421
A45: BOOK0003 | B45: 4941 | F45: Sao Tome and Principe | G45: 18 | I45: CUST0055 | J45: 8508
A46: BOOK0004 | B46: 6633 | F46: Saint Helena | G46: 18 | I46: CUST0057 | J46: 2423
A47: BOOK0005 | B47: 2518 | F47: Ecuador | G47: 18 | I47: CUST0060 | J47: 12154
A48: BOOK0006 | B48: 5801 | F48: Guyana | G48: 18 | I48: CUST0062 | J48: 7821
A49: BOOK0007 | B49: 5069 | F49: Oman | G49: 18 | I49: CUST0063 | J49: 10544
A50: BOOK0008 | B50: 5553 | F50: Algeria | G50: 18 | I50: CUST0064 | J50: 2808
A51: BOOK0009 | B51: 3961 | F51: Vietnam | G51: 17 | I51: CUST0065 | J51: 5034
A52: BOOK0010 | B52: 5983 | F52: Hungary | G52: 17 | I52: CUST0067 | J52: 6618
A53: BOOK0011 | B53: 5929 | F53: Mauritania | G53: 17 | I53: CUST0068 | J53: 8627
... A255: BOOK0213 | B255: 5196 | F255: Grand Total | G255: 3000 | I255: CUST0371 | J255: 5756
A256: BOOK0214 | B256: 6285 | I256: CUST0372 | J256: 8205
A257: BOOK0215 | B257: 2445 | I257: CUST0373 | J257: 4643
A258: BOOK0216 | B258: 5020 | I258: CUST0375 | J258: 11634
A259: BOOK0217 | B259: 4668 | I259: CUST0376 | J259: 5477
A260: BOOK0218 | B260: 3404 | I260: CUST0377 | J260: 9345
A261: BOOK0219 | B261: 4511 | I261: CUST0380 | J261: 19198
A262: BOOK0220 | B262: 5068 | I262: CUST0381 | J262: 3892
A263: BOOK0221 | B263: 6643 | I263: CUST0382 | J263: 5086
A264: BOOK0222 | B264: 6193 | I264: CUST0384 | J264: 6979
A265: BOOK0223 | B265: 5777 | I265: CUST0386 | J265: 2249
A266: BOOK0224 | B266: 2851 | I266: CUST0387 | J266: 9238
A267: BOOK0225 | B267: 7176 | I267: CUST0392 | J267: 5617
... A1897: BOOK1855 | B1897: 3015 | I1897: Grand Total | J1897: 14062080
A1898: BOOK1856 | B1898: 5343
A1899: BOOK1857 | B1899: 4352
A1900: BOOK1858 | B1900: 2630
A1901: BOOK1859 | B1901: 2624
A1902: BOOK1860 | B1902: 6773
A1903: BOOK1861 | B1903: 5805
A1904: BOOK1862 | B1904: 4012
A1905: BOOK1863 | B1905: 3577
A1906: BOOK1864 | B1906: 4000
A1907: BOOK1865 | B1907: 5250
A1908: BOOK1866 | B1908: 3935
A1909: BOOK1867 | B1909: 5020
... A3042: Grand Total | B3042: 4687.36

Sheet FactBookings
A1: BookingID | B1: CustomerID | C1: VisaID | D1: HotelID | E1: TicketID | F1: BookingDate | G1: Customer Name | H1: Gender | I1: National Country | J1: Visa Status | K1: Visa Country Applied | L1: Visa Submission Date | M1: Visa Fees | N1: Hotel | O1: City | P1: Night Rate | Q1: Ticket cost | R1: Tot cost
A2: BOOK0000 | B2: CUST0199 | C2: VISA2490 | D2: HOTEL0510 | E2: TICK1952 | F2: 45728 | G2: =VLOOKUP(Table1[[#This Row],[CustomerID]],DimCustomers!A:B,2,0) -> David Campbell | H2: =VLOOKUP(Table1[[#This Row],[CustomerID]],DimCustomers!A:C,3,0) -> Female | I2: =VLOOKUP(Table1[[#This Row],[CustomerID]],DimCustomers!A:D,4,0) -> Madagascar | J2: =VLOOKUP(Table1[[#This Row],[VisaID]],'DimVisaApplications 2'!A:C,3,0) -> Rejected | K2: =VLOOKUP(Table1[[#This Row],[VisaID]],'DimVisaApplications 2'!A:D,4,0) -> France | L2: =VLOOKUP(Table1[[#This Row],[VisaID]],'DimVisaApplications 2'!A:E,5,0) -> 45631 | M2: =VLOOKUP(Table1[[#This Row],[VisaID]],'DimVisaApplications 2'!A:G,7,0) -> 1642 | N2: =VLOOKUP(Table1[[#This Row],[HotelID]],DimHotels!A:B,2,0) -> Radisson | O2: =VLOOKUP(Table1[[#This Row],[HotelID]],DimHotels!A:C,3,0) -> Dubai | P2: =VLOOKUP(Table1[[#This Row],[HotelID]],DimHotels!A:E,5,0) -> 659 | Q2: =VLOOKUP(Table1[[#This Row],[TicketID]],DimTickets!A:G,7,0) -> 4668 | R2: =Table1[[#This Row],[Visa Fees]]+Table1[[#This Row],[Night Rate]]+Table1[[#This Row],[Ticket cost]] -> 6969
A3: BOOK0001 | B3: CUST0150 | C3: VISA0820 | D3: HOTEL1124 | E3: TICK2668 | F3: 45734 | G3: =VLOOKUP(Table1[[#This Row],[CustomerID]],DimCustomers!A:B,2,0) -> Jill Sherman | H3: =VLOOKUP(Table1[[#This Row],[CustomerID]],DimCustomers!A:C,3,0) -> Female | I3: =VLOOKUP(Table1[[#This Row],[CustomerID]],DimCustomers!A:D,4,0) -> Yemen | J3: =VLOOKUP(Table1[[#This Row],[VisaID]],'DimVisaApplications 2'!A:C,3,0) -> Approved | K3: =VLOOKUP(Table1[[#This Row],[VisaID]],'DimVisaApplications 2'!A:D,4,0) -> Canada | L3: =VLOOKUP(Table1[[#This Row],[VisaID]],'DimVisaApplications 2'!A:E,5,0) -> 45802 | M3: =VLOOKUP(Table1[[#This Row],[VisaID]],'DimVisaApplications 2'!A:G,7,0) -> 1182 | N3: =VLOOKUP(Table1[[#This Row],[HotelID]],DimHotels!A:B,2,0) -> Radisson | O3: =VLOOKUP(Table1[[#This Row],[HotelID]],DimHotels!A:C,3,0) -> Dubai | P3: =VLOOKUP(Table1[[#This Row],[HotelID]],DimHotels!A:E,5,0) -> 504 | Q3: =VLOOKUP(Table1[[#This Row],[TicketID]],DimTickets!A:G,7,0) -> 3023 | R3: =Table1[[#This Row],[Visa Fees]]+Table1[[#This Row],[Night Rate]]+Table1[[#This Row],[Ticket cost]] -> 4709
A4: BOOK0002 | B4: CUST0155 | C4: VISA1448 | D4: HOTEL0191 | E4: TICK0994 | F4: 45783 | G4: =VLOOKUP(Table1[[#This Row],[CustomerID]],DimCustomers!A:B,2,0) -> Stacy Chan | H4: =VLOOKUP(Table1[[#This Row],[CustomerID]],DimCustomers!A:C,3,0) -> Female | I4: =VLOOKUP(Table1[[#This Row],[CustomerID]],DimCustomers!A:D,4,0) -> United Kingdom | J4: =VLOOKUP(Table1[[#This Row],[VisaID]],'DimVisaApplications 2'!A:C,3,0) -> Approved | K4: =VLOOKUP(Table1[[#This Row],[VisaID]],'DimVisaApplications 2'!A:D,4,0) -> USA | L4: =VLOOKUP(Table1[[#This Row],[VisaID]],'DimVisaApplications 2'!A:E,5,0) -> 45526 | M4: =VLOOKUP(Table1[[#This Row],[VisaID]],'DimVisaApplications 2'!A:G,7,0) -> 682 | N4: =VLOOKUP(Table1[[#This Row],[HotelID]],DimHotels!A:B,2,0) -> Four Seasons | O4: =VLOOKUP(Table1[[#This Row],[HotelID]],DimHotels!A:C,3,0) -> Cairo | P4: =VLOOKUP(Table1[[#This Row],[HotelID]],DimHotels!A:E,5,0) -> 384 | Q4: =VLOOKUP(Table1[[#This Row],[TicketID]],DimTickets!A:G,7,0) -> 3099 | R4: =Table1[[#This Row],[Visa Fees]]+Table1[[#This Row],[Night Rate]]+Table1[[#This Row],[Ticket cost]] -> 4165
A5: BOOK0003 | B5: CUST0000 | C5: VISA1351 | D5: HOTEL2220 | E5: TICK0046 | F5: 45812 | G5: =VLOOKUP(Table1[[#This Row],[CustomerID]],DimCustomers!A:B,2,0) -> Norma Fisher | H5: =VLOOKUP(Table1[[#This Row],[CustomerID]],DimCustomers!A:C,3,0) -> Female | I5: =VLOOKUP(Table1[[#This Row],[CustomerID]],DimCustomers!A:D,4,0) -> Gabon | J5: =VLOOKUP(Table1[[#This Row],[VisaID]],'DimVisaApplications 2'!A:C,3,0) -> Approved | K5: =VLOOKUP(Table1[[#This Row],[VisaID]],'DimVisaApplications 2'!A:D,4,0) -> UAE | L5: =VLOOKUP(Table1[[#This Row],[VisaID]],'DimVisaApplications 2'!A:E,5,0) -> 45828 | M5: =VLOOKUP(Table1[[#This Row],[VisaID]],'DimVisaApplications 2'!A:G,7,0) -> 1575 | N5: =VLOOKUP(Table1[[#This Row],[HotelID]],DimHotels!A:B,2,0) -> Hilton | O5: =VLOOKUP(Table1[[#This Row],[HotelID]],DimHotels!A:C,3,0) -> New York | P5: =VLOOKUP(Table1[[#This Row],[HotelID]],DimHotels!A:E,5,0) -> 331 | Q5: =VLOOKUP(Table1[[#This Row],[TicketID]],DimTickets!A:G,7,0) -> 3035 | R5: =Table1[[#This Row],[Visa Fees]]+Table1[[#This Row],[Night Rate]]+Table1[[#This Row],[Ticket cost]] -> 4941
A6: BOOK0004 | B6: CUST0370 | C6: VISA2615 | D6: HOTEL1280 | E6: TICK1867 | F6: 45683 | G6: =VLOOKUP(Table1[[#This Row],[CustomerID]],DimCustomers!A:B,2,0) -> Kevin Miller | H6: =VLOOKUP(Table1[[#This Row],[CustomerID]],DimCustomers!A:C,3,0) -> Male | I6: =VLOOKUP(Table1[[#This Row],[CustomerID]],DimCustomers!A:D,4,0) -> Haiti | J6: =VLOOKUP(Table1[[#This Row],[VisaID]],'DimVisaApplications 2'!A:C,3,0) -> Approved | K6: =VLOOKUP(Table1[[#This Row],[VisaID]],'DimVisaApplications 2'!A:D,4,0) -> UAE | L6: =VLOOKUP(Table1[[#This Row],[VisaID]],'DimVisaApplications 2'!A:E,5,0) -> 45545 | M6: =VLOOKUP(Table1[[#This Row],[VisaID]],'DimVisaApplications 2'!A:G,7,0) -> 1213 | N6: =VLOOKUP(Table1[[#This Row],[HotelID]],DimHotels!A:B,2,0) -> Hilton | O6: =VLOOKUP(Table1[[#This Row],[HotelID]],DimHotels!A:C,3,0) -> Dubai | P6: =VLOOKUP(Table1[[#This Row],[HotelID]],DimHotels!A:E,5,0) -> 626 | Q6: =VLOOKUP(Table1[[#This Row],[TicketID]],DimTickets!A:G,7,0) -> 4794 | R6: =Table1[[#This Row],[Visa Fees]]+Table1[[#This Row],[Night Rate]]+Table1[[#This Row],[Ticket cost]] -> 6633
A7: BOOK0005 | B7: CUST1634 | C7: VISA0517 | D7: HOTEL0886 | E7: TICK0662 | F7: 45750 | G7: =VLOOKUP(Table1[[#This Row],[CustomerID]],DimCustomers!A:B,2,0) -> Joshua Baker | H7: =VLOOKUP(Table1[[#This Row],[CustomerID]],DimCustomers!A:C,3,0) -> Male | I7: =VLOOKUP(Table1[[#This Row],[CustomerID]],DimCustomers!A:D,4,0) -> Sao Tome and Principe | J7: =VLOOKUP(Table1[[#This Row],[VisaID]],'DimVisaApplications 2'!A:C,3,0) -> Pending | K7: =VLOOKUP(Table1[[#This Row],[VisaID]],'DimVisaApplications 2'!A:D,4,0) -> Germany | L7: =VLOOKUP(Table1[[#This Row],[VisaID]],'DimVisaApplications 2'!A:E,5,0) -> 45684 | M7: =VLOOKUP(Table1[[#This Row],[VisaID]],'DimVisaApplications 2'!A:G,7,0) -> 845 | N7: =VLOOKUP(Table1[[#This Row],[HotelID]],DimHotels!A:B,2,0) -> Hilton | O7: =VLOOKUP(Table1[[#This Row],[HotelID]],DimHotels!A:C,3,0) -> New York | P7: =VLOOKUP(Table1[[#This Row],[HotelID]],DimHotels!A:E,5,0) -> 637 | Q7: =VLOOKUP(Table1[[#This Row],[TicketID]],DimTickets!A:G,7,0) -> 1036 | R7: =Table1[[#This Row],[Visa Fees]]+Table1[[#This Row],[Night Rate]]+Table1[[#This Row],[Ticket cost]] -> 2518
A8: BOOK0006 | B8: CUST2992 | C8: VISA2833 | D8: HOTEL2474 | E8: TICK2513 | F8: 45831 | G8: =VLOOKUP(Table1[[#This Row],[CustomerID]],DimCustomers!A:B,2,0) -> Becky Wood | H8: =VLOOKUP(Table1[[#This Row],[CustomerID]],DimCustomers!A:C,3,0) -> Female | I8: =VLOOKUP(Table1[[#This Row],[CustomerID]],DimCustomers!A:D,4,0) -> Cape Verde | J8: =VLOOKUP(Table1[[#This Row],[VisaID]],'DimVisaApplications 2'!A:C,3,0) -> Approved | K8: =VLOOKUP(Table1[[#This Row],[VisaID]],'DimVisaApplications 2'!A:D,4,0) -> France | L8: =VLOOKUP(Table1[[#This Row],[VisaID]],'DimVisaApplications 2'!A:E,5,0) -> 45505 | M8: =VLOOKUP(Table1[[#This Row],[VisaID]],'DimVisaApplications 2'!A:G,7,0) -> 704 | N8: =VLOOKUP(Table1[[#This Row],[HotelID]],DimHotels!A:B,2,0) -> Radisson | O8: =VLOOKUP(Table1[[#This Row],[HotelID]],DimHotels!A:C,3,0) -> Cairo | P8: =VLOOKUP(Table1[[#This Row],[HotelID]],DimHotels!A:E,5,0) -> 563 | Q8: =VLOOKUP(Table1[[#This Row],[TicketID]],DimTickets!A:G,7,0) -> 4534 | R8: =Table1[[#This Row],[Visa Fees]]+Table1[[#This Row],[Night Rate]]+Table1[[#This Row],[Ticket cost]] -> 5801
A9: BOOK0007 | B9: CUST0069 | C9: VISA1360 | D9: HOTEL0517 | E9: TICK1248 | F9: 45774 | G9: =VLOOKUP(Table1[[#This Row],[CustomerID]],DimCustomers!A:B,2,0) -> Eric Owens PhD | H9: =VLOOKUP(Table1[[#This Row],[CustomerID]],DimCustomers!A:C,3,0) -> Male | I9: =VLOOKUP(Table1[[#This Row],[CustomerID]],DimCustomers!A:D,4,0) -> United States Minor Outlying Islands | J9: =VLOOKUP(Table1[[#This Row],[VisaID]],'DimVisaApplications 2'!A:C,3,0) -> Rejected | K9: =VLOOKUP(Table1[[#This Row],[VisaID]],'DimVisaApplications 2'!A:D,4,0) -> USA | L9: =VLOOKUP(Table1[[#This Row],[VisaID]],'DimVisaApplications 2'!A:E,5,0) -> 45628 | M9: =VLOOKUP(Table1[[#This Row],[VisaID]],'DimVisaApplications 2'!A:G,7,0) -> 1372 | N9: =VLOOKUP(Table1[[#This Row],[HotelID]],DimHotels!A:B,2,0) -> Radisson | O9: =VLOOKUP(Table1[[#This Row],[HotelID]],DimHotels!A:C,3,0) -> Paris | P9: =VLOOKUP(Table1[[#This Row],[HotelID]],DimHotels!A:E,5,0) -> 750 | Q9: =VLOOKUP(Table1[[#This Row],[TicketID]],DimTickets!A:G,7,0) -> 2947 | R9: =Table1[[#This Row],[Visa Fees]]+Table1[[#This Row],[Night Rate]]+Table1[[#This Row],[Ticket cost]] -> 5069
A10: BOOK0008 | B10: CUST0284 | C10: VISA1131 | D10: HOTEL2644 | E10: TICK1581 | F10: 45752 | G10: =VLOOKUP(Table1[[#This Row],[CustomerID]],DimCustomers!A:B,2,0) -> Tonya Cooper | H10: =VLOOKUP(Table1[[#This Row],[CustomerID]],DimCustomers!A:C,3,0) -> Female | I10: =VLOOKUP(Table1[[#This Row],[CustomerID]],DimCustomers!A:D,4,0) -> Ghana | J10: =VLOOKUP(Table1[[#This Row],[VisaID]],'DimVisaApplications 2'!A:C,3,0) -> Approved | K10: =VLOOKUP(Table1[[#This Row],[VisaID]],'DimVisaApplications 2'!A:D,4,0) -> Canada | L10: =VLOOKUP(Table1[[#This Row],[VisaID]],'DimVisaApplications 2'!A:E,5,0) -> 45835 | M10: =VLOOKUP(Table1[[#This Row],[VisaID]],'DimVisaApplications 2'!A:G,7,0) -> 1779 | N10: =VLOOKUP(Table1[[#This Row],[HotelID]],DimHotels!A:B,2,0) -> Four Seasons | O10: =VLOOKUP(Table1[[#This Row],[HotelID]],DimHotels!A:C,3,0) -> New York | P10: =VLOOKUP(Table1[[#This Row],[HotelID]],DimHotels!A:E,5,0) -> 282 | Q10: =VLOOKUP(Table1[[#This Row],[TicketID]],DimTickets!A:G,7,0) -> 3492 | R10: =Table1[[#This Row],[Visa Fees]]+Table1[[#This Row],[Night Rate]]+Table1[[#This Row],[Ticket cost]] -> 5553
A11: BOOK0009 | B11: CUST0316 | C11: VISA0606 | D11: HOTEL0879 | E11: TICK0524 | F11: 45734 | G11: =VLOOKUP(Table1[[#This Row],[CustomerID]],DimCustomers!A:B,2,0) -> Lauren Parsons | H11: =VLOOKUP(Table1[[#This Row],[CustomerID]],DimCustomers!A:C,3,0) -> Female | I11: =VLOOKUP(Table1[[#This Row],[CustomerID]],DimCustomers!A:D,4,0) -> Poland | J11: =VLOOKUP(Table1[[#This Row],[VisaID]],'DimVisaApplications 2'!A:C,3,0) -> Pending | K11: =VLOOKUP(Table1[[#This Row],[VisaID]],'DimVisaApplications 2'!A:D,4,0) -> USA | L11: =VLOOKUP(Table1[[#This Row],[VisaID]],'DimVisaApplications 2'!A:E,5,0) -> 45648 | M11: =VLOOKUP(Table1[[#This Row],[VisaID]],'DimVisaApplications 2'!A:G,7,0) -> 539 | N11: =VLOOKUP(Table1[[#This Row],[HotelID]],DimHotels!A:B,2,0) -> Hilton | O11: =VLOOKUP(Table1[[#This Row],[HotelID]],DimHotels!A:C,3,0) -> London | P11: =VLOOKUP(Table1[[#This Row],[HotelID]],DimHotels!A:E,5,0) -> 714 | Q11: =VLOOKUP(Table1[[#This Row],[TicketID]],DimTickets!A:G,7,0) -> 2708 | R11: =Table1[[#This Row],[Visa Fees]]+Table1[[#This Row],[Night Rate]]+Table1[[#This Row],[Ticket cost]] -> 3961
A12: BOOK0010 | B12: CUST0022 | C12: VISA1070 | D12: HOTEL1153 | E12: TICK1296 | F12: 45847 | G12: =VLOOKUP(Table1[[#This Row],[CustomerID]],DimCustomers!A:B,2,0) -> Janice Johnston | H12: =VLOOKUP(Table1[[#This Row],[CustomerID]],DimCustomers!A:C,3,0) -> Female | I12: =VLOOKUP(Table1[[#This Row],[CustomerID]],DimCustomers!A:D,4,0) -> China | J12: =VLOOKUP(Table1[[#This Row],[VisaID]],'DimVisaApplications 2'!A:C,3,0) -> Approved | K12: =VLOOKUP(Table1[[#This Row],[VisaID]],'DimVisaApplications 2'!A:D,4,0) -> Canada | L12: =VLOOKUP(Table1[[#This Row],[VisaID]],'DimVisaApplications 2'!A:E,5,0) -> 45614 | M12: =VLOOKUP(Table1[[#This Row],[VisaID]],'DimVisaApplications 2'!A:G,7,0) -> 1293 | N12: =VLOOKUP(Table1[[#This Row],[HotelID]],DimHotels!A:B,2,0) -> Hilton | O12: =VLOOKUP(Table1[[#This Row],[HotelID]],DimHotels!A:C,3,0) -> New York | P12: =VLOOKUP(Table1[[#This Row],[HotelID]],DimHotels!A:E,5,0) -> 603 | Q12: =VLOOKUP(Table1[[#This Row],[TicketID]],DimTickets!A:G,7,0) -> 4087 | R12: =Table1[[#This Row],[Visa Fees]]+Table1[[#This Row],[Night Rate]]+Table1[[#This Row],[Ticket cost]] -> 5983
A13: BOOK0011 | B13: CUST0268 | C13: VISA1155 | D13: HOTEL2979 | E13: TICK2486 | F13: 45778 | G13: =VLOOKUP(Table1[[#This Row],[CustomerID]],DimCustomers!A:B,2,0) -> Mark Mitchell | H13: =VLOOKUP(Table1[[#This Row],[CustomerID]],DimCustomers!A:C,3,0) -> Female | I13: =VLOOKUP(Table1[[#This Row],[CustomerID]],DimCustomers!A:D,4,0) -> United Arab Emirates | J13: =VLOOKUP(Table1[[#This Row],[VisaID]],'DimVisaApplications 2'!A:C,3,0) -> Pending | K13: =VLOOKUP(Table1[[#This Row],[VisaID]],'DimVisaApplications 2'!A:D,4,0) -> UK | L13: =VLOOKUP(Table1[[#This Row],[VisaID]],'DimVisaApplications 2'!A:E,5,0) -> 45762 | M13: =VLOOKUP(Table1[[#This Row],[VisaID]],'DimVisaApplications 2'!A:G,7,0) -> 693 | N13: =VLOOKUP(Table1[[#This Row],[HotelID]],DimHotels!A:B,2,0) -> Sheraton | O13: =VLOOKUP(Table1[[#This Row],[HotelID]],DimHotels!A:C,3,0) -> New York | P13: =VLOOKUP(Table1[[#This Row],[HotelID]],DimHotels!A:E,5,0) -> 709 | Q13: =VLOOKUP(Table1[[#This Row],[TicketID]],DimTickets!A:G,7,0) -> 4527 | R13: =Table1[[#This Row],[Visa Fees]]+Table1[[#This Row],[Night Rate]]+Table1[[#This Row],[Ticket cost]] -> 5929
... A3001: BOOK2999 | B3001: CUST0563 | C3001: VISA1157 | D3001: HOTEL1887 | E3001: TICK2964 | F3001: 45735 | G3001: =VLOOKUP(Table1[[#This Row],[CustomerID]],DimCustomers!A:B,2,0) -> Colleen Cruz | H3001: =VLOOKUP(Table1[[#This Row],[CustomerID]],DimCustomers!A:C,3,0) -> Female | I3001: =VLOOKUP(Table1[[#This Row],[CustomerID]],DimCustomers!A:D,4,0) -> Liechtenstein | J3001: =VLOOKUP(Table1[[#This Row],[VisaID]],'DimVisaApplications 2'!A:C,3,0) -> Rejected | K3001: =VLOOKUP(Table1[[#This Row],[VisaID]],'DimVisaApplications 2'!A:D,4,0) -> Canada | L3001: =VLOOKUP(Table1[[#This Row],[VisaID]],'DimVisaApplications 2'!A:E,5,0) -> 45798 | M3001: =VLOOKUP(Table1[[#This Row],[VisaID]],'DimVisaApplications 2'!A:G,7,0) -> 1815 | N3001: =VLOOKUP(Table1[[#This Row],[HotelID]],DimHotels!A:B,2,0) -> Marriott | O3001: =VLOOKUP(Table1[[#This Row],[HotelID]],DimHotels!A:C,3,0) -> New York | P3001: =VLOOKUP(Table1[[#This Row],[HotelID]],DimHotels!A:E,5,0) -> 629 | Q3001: =VLOOKUP(Table1[[#This Row],[TicketID]],DimTickets!A:G,7,0) -> 2483 | R3001: =Table1[[#This Row],[Visa Fees]]+Table1[[#This Row],[Night Rate]]+Table1[[#This Row],[Ticket cost]] -> 4927

Sheet DimVisaApplications 2
A1: VisaID | B1: VisaType | C1: Status | D1: CountryApplied | E1: SubmissionDate | F1: ApprovedDate | G1: Fees | H1: Processing time 2
A2: VISA0000 | B2: Business | C2: Rejected | D2: Canada | E2: 45861 | F2: 8/4/2025 | G2: 1138 | H2: 12
A3: VISA0001 | B3: Business | C3: Rejected | D3: France | E3: 45829 | F3: 7/30/2025 | G3: 1766 | H3: 39
A4: VISA0002 | B4: Student | C4: Rejected | D4: UK | E4: 45596 | F4: 8/11/2025 | G4: 1656 | H4: 284
A5: VISA0003 | B5: Student | C5: Approved | D5: France | E5: 45822 | F5: 8/8/2025 | G5: 1872 | H5: 55
A6: VISA0004 | B6: Student | C6: Pending | D6: UAE | E6: 45853 | F6: 8/1/2025 | G6: 1515 | H6: 17
A7: VISA0005 | B7: Tourist | C7: Approved | D7: Canada | E7: 45614 | F7: Unknown | G7: 1683 | H7: Unknown
A8: VISA0006 | B8: Tourist | C8: Pending | D8: UAE | E8: 45776 | F8: 8/20/2025 | G8: 858 | H8: 113
A9: VISA0007 | B9: Business | C9: Rejected | D9: Canada | E9: 45539 | F9: 8/3/2025 | G9: 1763 | H9: 333
A10: VISA0008 | B10: Student | C10: Pending | D10: France | E10: 45825 | F10: 8/15/2025 | G10: 1701 | H10: 59
A11: VISA0009 | B11: Business | C11: Pending | D11: Germany | E11: 45793 | F11: 8/9/2025 | G11: 1046 | H11: 85
A12: VISA0010 | B12: Business | C12: Rejected | D12: UK | E12: 45509 | F12: Unknown | G12: 882 | H12: Unknown
A13: VISA0011 | B13: Student | C13: Pending | D13: France | E13: 45789 | F13: 8/1/2025 | G13: 904 | H13: 81
... A3001: VISA2999 | B3001: Student | C3001: Approved | D3001: Germany | E3001: 45796 | F3001: Unknown | G3001: 1927 | H3001: Unknown
